damv1time7/__init__.py
damv1time7/mydump.py
damv1time7/mylogger.py
damv1time7/mytime7.py
damv1time7-0.6.4.dist-info/LICENSE
damv1time7-0.6.4.dist-info/METADATA
damv1time7-0.6.4.dist-info/WHEEL
damv1time7-0.6.4.dist-info/top_level.txt
damv1time7-0.6.4.dist-info/RECORD
