Metadata-Version: 2.1
Name: damv1time7
Version: 0.6.4
Summary: time with zone+7 package
Home-page: UNKNOWN
Author: dhonyabumuhammad (Bekasi)
Author-email: <baba-rtw24133@tutamail.com>
License: UNKNOWN
Keywords: timezoneplus7
Platform: UNKNOWN
Classifier: Development Status :: 4 - Beta
Classifier: Intended Audience :: Developers
Classifier: Operating System :: Unix
Classifier: Operating System :: MacOS :: MacOS X
Classifier: Operating System :: Microsoft :: Windows
Classifier: Programming Language :: Python :: 3
Classifier: Programming Language :: Python :: 3.7
Classifier: Programming Language :: Python :: 3.8
Classifier: Programming Language :: Python :: 3.9
Classifier: Programming Language :: Python :: 3.10
Classifier: Topic :: Software Development :: Debuggers
Classifier: License :: OSI Approved :: MIT License
Requires-Python: >=3.0
License-File: LICENSE
Requires-Dist: time-uuid==0.2.0
Requires-Dist: damv1manipulation==0.0.14
